odoo/addons/hr_utilization_report/README.rst
odoo/addons/hr_utilization_report/__init__.py
odoo/addons/hr_utilization_report/__manifest__.py
odoo/addons/hr_utilization_report/i18n/de.po
odoo/addons/hr_utilization_report/i18n/es.po
odoo/addons/hr_utilization_report/i18n/fr.po
odoo/addons/hr_utilization_report/i18n/hr_utilization_report.pot
odoo/addons/hr_utilization_report/readme/CONTRIBUTORS.rst
odoo/addons/hr_utilization_report/readme/DESCRIPTION.rst
odoo/addons/hr_utilization_report/readme/ROADMAP.rst
odoo/addons/hr_utilization_report/readme/USAGE.rst
odoo/addons/hr_utilization_report/report/__init__.py
odoo/addons/hr_utilization_report/report/hr_utilization_report.py
odoo/addons/hr_utilization_report/report/hr_utilization_report.xml
odoo/addons/hr_utilization_report/static/description/icon.png
odoo/addons/hr_utilization_report/static/description/index.html
odoo/addons/hr_utilization_report/tests/__init__.py
odoo/addons/hr_utilization_report/tests/test_hr_utilization_report.py
odoo/addons/hr_utilization_report/views/hr_department.xml
odoo/addons/hr_utilization_report/views/hr_employee.xml
odoo/addons/hr_utilization_report/wizards/__init__.py
odoo/addons/hr_utilization_report/wizards/hr_utilization_report_wizard.py
odoo/addons/hr_utilization_report/wizards/hr_utilization_report_wizard.xml
odoo12_addon_hr_utilization_report-12.0.1.0.3.dist-info/METADATA
odoo12_addon_hr_utilization_report-12.0.1.0.3.dist-info/WHEEL
odoo12_addon_hr_utilization_report-12.0.1.0.3.dist-info/top_level.txt
odoo12_addon_hr_utilization_report-12.0.1.0.3.dist-info/RECORD
